{
  "Result":{
    "TripId":3333625,
    "Price":{
      "Value":10,
      "Currency":"BYN"
    },
    "TwoOnBackseat":true,
    "SeatsAvailable":0,
    "SeatsTotal":1,
    "WomenOnly":false,
    "Distance":{
      "Number":170,
      "Unit":"KM"
    },
    "BaggageType":2,
    "Animals":false,
    "Smoking":true,
    "Children":false,
    "AutoConfirmation":true,
    "Car":{
      "CarId":271061,
      "Brand":{
        "Id":102,
        "Name":"Volkswagen"
      },
      "Model":{
        "Id":1413,
        "Name":"Passat"
      },
      "Color":"FFFFFF",
      "Year":0,
      "Avatars":{
        "Original":"https://api.beepcar.ru/v1/cars/271061/avatars/original/68971690300E9D7FCBB3E1E9B89863B80FE1D26E",
        "150_150":"https://api.beepcar.ru/v1/cars/271061/avatars/150x150/7F72A4A6C547D6EEE8CB8DF5227581444C411BEE",
        "Resized150_150":"https://api.beepcar.ru/v1/cars/271061/avatars/150x150/7F72A4A6C547D6EEE8CB8DF5227581444C411BEE"
      },
      "Verified":false,
      "Blocked":false,
      "DocumentsStatuses":{

      }
    },
    "Points":[
      {
        "Id":242978905,
        "Name":"Ивацевичи",
        "NameEn":"Ivacevichi",
        "NameRu":"Ивацевичи",
        "Region":"Брестская область",
        "Country":"Республика Беларусь",
        "Coordinates":{
          "Lat":52.7090541,
          "Lon":25.3426959
        },
        "MapProvider":"google",
        "Time":"2017-09-03T17:00:00+03:00",
        "EndPoint":true
      },
      {
        "Id":242979018,
        "Name":"Ружаны",
        "NameEn":"",
        "NameRu":"Ружаны",
        "Region":"Брестская область",
        "Country":"Республика Беларусь",
        "Coordinates":{
          "Lat":52.8648175,
          "Lon":24.8917048
        },
        "MapProvider":"google",
        "Time":"2017-09-03T17:30:00+03:00"
      },
      {
        "Id":1153145528,
        "Name":"Волковыск",
        "NameEn":"Vawkavysk",
        "NameRu":"Волковыск",
        "Region":"Гродненская область",
        "Country":"Республика Беларусь",
        "Coordinates":{
          "Lat":53.1539638,
          "Lon":24.4489454
        },
        "MapProvider":"google",
        "Time":"2017-09-03T18:10:00+03:00"
      },
      {
        "Id":428339511,
        "Name":"Гродно",
        "NameEn":"Hrodna",
        "NameRu":"Гродно",
        "Region":"Гродненская область",
        "Country":"Республика Беларусь",
        "Coordinates":{
          "Lat":53.6834599,
          "Lon":23.8342648
        },
        "MapProvider":"google",
        "Time":"2017-09-03T19:20:00+03:00",
        "EndPoint":true
      }
    ],
    "Started":true,
    "Finished":true,
    "Deleted":false,
    "Comments":[
      {
        "ID":1616356,
        "User":{
          "Activity":{
            "Online":false,
            "LastVisitTime":"2017-10-04T20:29:07+03:00",
            "LastVisitPlatform":"android"
          },
          "Age":25,
          "Avatars":{
            "150_150":"https://api.beepcar.ru/v1/users/31324595/avatars/150x150/E252B09A61464F9F57A802B59BFE4270A5A16DED",
            "Original":"https://api.beepcar.ru/v1/users/31324595/avatars/original/63E9800FD9D8A74E569C52222C84C64D4CB77D82",
            "Resized150_150":"https://api.beepcar.ru/v1/users/31324595/avatars/150x150/E252B09A61464F9F57A802B59BFE4270A5A16DED"
          },
          "CommittedReviewsCount":6,
          "DocumentsStatuses":{

          },
          "EmailVerified":true,
          "Gender":"male",
          "Id":3.1324595e+07,
          "MaskedPhone":"37533*******",
          "Name":"Александр",
          "PhoneVerified":true,
          "Rating":5,
          "RegistrationDate":"2017-07-03T13:50:40Z",
          "ReviewInfos":[
            {
              "FinishStatus":"ShowReview",
              "Status":"forbidden"
            }
          ],
          "ReviewStatus":"forbidden",
          "ReviewsCount":3,
          "Verified":false
        },
        "Text":"время можно корректировать в вашу пользу",
        "MessageTime":"2017-09-02T18:10:17Z",
        "FromDriver":true,
        "CommenterRole":"Driver"
      }
    ],
    "CommentsCount":1,
    "Appeals":{
      "Car":"unable",
      "CarAvatar":"unable",
      "MeetPoints":[
        {
          "LocationId":242978905,
          "Status":"able"
        },
        {
          "LocationId":242979018,
          "Status":"able"
        },
        {
          "LocationId":1153145528,
          "Status":"able"
        },
        {
          "LocationId":428339511,
          "Status":"able"
        }
      ]
    },
    "Description":"",
    "Driver":{
      "Activity":{
        "Online":false,
        "LastVisitTime":"2017-10-04T20:29:07+03:00",
        "LastVisitPlatform":"android"
      },
      "Age":25,
      "Appeals":{
        "Avatar":"unable",
        "Info":"able",
        "Passport":"able"
      },
      "Avatars":{
        "150_150":"https://api.beepcar.ru/v1/users/31324595/avatars/150x150/E252B09A61464F9F57A802B59BFE4270A5A16DED",
        "Original":"https://api.beepcar.ru/v1/users/31324595/avatars/original/63E9800FD9D8A74E569C52222C84C64D4CB77D82",
        "Resized150_150":"https://api.beepcar.ru/v1/users/31324595/avatars/150x150/E252B09A61464F9F57A802B59BFE4270A5A16DED"
      },
      "CommittedReviewsCount":6,
      "DocumentsStatuses":{

      },
      "EmailVerified":true,
      "Gender":"male",
      "Id":3.1324595e+07,
      "MaskedPhone":"37533*******",
      "Name":"Александр",
      "PhoneVerified":true,
      "Rating":5,
      "RegistrationDate":"2017-07-03T16:50:40+03:00",
      "ReviewInfos":[
        {
          "FinishStatus":"ShowReview",
          "Status":"forbidden"
        }
      ],
      "ReviewStatus":"forbidden",
      "ReviewsCount":3,
      "SocialNetworks":[
        {
          "FriendsCount":171,
          "Type":"vk"
        }
      ],
      "Verified":false
    },
    "Requests":[
      {
        "ID":1301028,
        "TripId":3333625,
        "Passenger":{
          "Age":35,
          "Appeals":{
            "Avatar":"unable",
            "Info":"able",
            "Passport":"able"
          },
          "Avatars":{
            "150_150":"https://api.beepcar.ru/v1/users/54433027/avatars/150x150/F055F60FCAF996E1AEC36E3583C5B781BE2B7D8D",
            "Original":"https://api.beepcar.ru/v1/users/54433027/avatars/original/2DF612248069BD0332668146D66AAE0799CA7DC0",
            "Resized150_150":"https://api.beepcar.ru/v1/users/54433027/avatars/150x150/F055F60FCAF996E1AEC36E3583C5B781BE2B7D8D"
          },
          "CommittedReviewsCount":0,
          "DocumentsStatuses":{

          },
          "EmailVerified":false,
          "Gender":"female",
          "Id":5.4433027e+07,
          "MaskedPhone":"37525*******",
          "Name":"Александра",
          "PhoneVerified":true,
          "Rating":5,
          "RegistrationDate":"2017-09-03T16:15:40+03:00",
          "ReviewInfos":[
            {
              "FinishStatus":"ShowReview",
              "Status":"forbidden"
            }
          ],
          "ReviewStatus":"forbidden",
          "ReviewsCount":1,
          "SocialNetworks":[
            {
              "FriendsCount":69,
              "Type":"vk"
            }
          ],
          "Verified":false
        },
        "FromLocation":{
          "Id":1153145528,
          "Name":"Волковыск",
          "NameEn":"Vawkavysk",
          "NameRu":"Волковыск",
          "Region":"Гродненская область",
          "Country":"Республика Беларусь",
          "Coordinates":{
            "Lat":53.1539638,
            "Lon":24.4489454
          },
          "MapProvider":"google",
          "Time":"2017-09-03T18:10:00+03:00"
        },
        "ToLocation":{
          "Id":428339511,
          "Name":"Гродно",
          "NameEn":"Hrodna",
          "NameRu":"Гродно",
          "Region":"Гродненская область",
          "Country":"Республика Беларусь",
          "Coordinates":{
            "Lat":53.6834599,
            "Lon":23.8342648
          },
          "MapProvider":"google",
          "Time":"2017-09-03T19:20:00+03:00"
        },
        "NSeats":1,
        "Status":"Approved"
      }
    ],
    "ViewersCount":1,
    "TimesViewed":82,
    "MapProvider":"google"
  }
}
